{
    "source_file": "./raw_volume-zh/volume1/exercise7.tex",
    "problem_type": "proof",
    "problem": "问题7 在一个由 $n$ 个方格组成的 $1 \\times n$ 棋盘中的每个方格上各放一个钱币.\n第一次搬动是将某一个方格上的钱币放在相邻的一个方格中的钱币上, 左边或右边都可以,但是不能出棋盘.\n以后的每次搬动是将某个方格中的所有钱币 (设有 $k$ 个) 搬到与此方格相邻的第 $k$ 个位置的方格中, 左或右都可以,但是不能出棋盘.\n试证: 能经过 $n-1$ 次搬动, 将所有钱币都集中在一个方格中.",
    "solution": "设 $n$ 为奇数, 记 $n=2 m+1$. 考虑第 $m+1$ 个方格, 将其中钱币向左运动一次, 于是第 $m$ 个方格中有两个钱币, 而第 $m+1$ 个方格中无钱币.\n将第 $m$ 个方格中的钱币搬到第 $m+2$ 个方格中, 这样依次从左到右, 再从右到左, 经过 $n-1$ 次运动, 便将钱币都放在最右边那个方格中, 而其余方格中无钱币.\n设 $n$ 为偶数, 记 $n=2 m$. 考虑第 $m$ 个方格, 将其中钱币向右运动一次, 于是第 $m+1$ 个方格中有两个钱币, 而第 $m$ 个方格中无钱币.\n将第 $m+1$ 个方格中的钱币搬到第 $m^{--} 1$ 个方格中, 这样依次从右到左, 再从左到右, 经过 $n-1$ 次运动,便将钱币都放在最右边那个方格中,而其余方格中无钱币.",
    "remark": "",
    "figures": []
}