{
    "source_file": "./raw_volume-zh/volume4/chapter2-3.tex",
    "problem_type": "proof",
    "problem": "例9. 设 $A B C D E F$ 是凸六边形, 且 $A B / / E D, B C / / F E, C D / / A F$. 又设 $R_A 、 R_C 、 R_E$ 分别表示 $\\triangle F A B 、 \\triangle B C D 、 \\triangle D E F$ 的外接圆半径, $p$ 表示六边形的周长, 证明:\n$$\nR_A+R_B+R_C \\geqslant \\frac{p}{2}\n$$",
    "solution": "证明:过点 $A$ 作 $B C$ 的垂线,记该垂线夹在平行线 $E F 、 B C$ 之间线段的长度为 $h$, 设 $A B 、 B C 、 C D 、 D E 、 E F 、 F A$ 的长度分别为 $a 、 b 、 c 、 d 、 e 、 f$. 则\n$$\nB F \\geqslant h=a \\sin B+f \\sin F .\n$$\n由于\n$A B / / D E, B C / / E F, A F / / C D$,\n所以\n$$\n\\begin{gathered}\n\\angle A=\\angle D, \\angle B=\\angle E, \\angle C=\\angle F . \\\\\n2 R_A=\\frac{B F}{\\sin A} \\geqslant a \\frac{\\sin B}{\\sin A}+f \\frac{\\sin F}{\\sin A} .\n\\end{gathered}\n$$\n同理可得\n$$\n\\begin{aligned}\n& 2 R_C=\\frac{B D}{\\sin C} \\geqslant b \\frac{\\sin B}{\\sin C}+c \\frac{\\sin D}{\\sin C}, \\\\\n& 2 R_E=\\frac{D F}{\\sin E} \\geqslant d \\frac{\\sin D}{\\sin E}+e \\frac{\\sin F}{\\sin E},\n\\end{aligned}\n$$\n所以\n$$\n\\begin{aligned}\n& 2\\left(R_A+R_C+R_E\\right) \\\\\n\\geqslant & a \\frac{\\sin B}{\\sin A}+b \\frac{\\sin B}{\\sin C}+c \\frac{\\sin D}{\\sin C}+d \\frac{\\sin D}{\\sin E}+e \\frac{\\sin F}{\\sin E}+f \\frac{\\sin F}{\\sin A} .\n\\end{aligned}\n$$\n分两种情况讨论:\n(1)当 $a=d$ 时,由题设\n$$\nA B / / D E, B C / / E F, C D / / F A,\n$$\n则\n$$\n\\begin{aligned}\n& 2\\left(R_A+R_C+R_E\\right) \\\\\n\\geqslant & a\\left(\\frac{\\sin B}{\\sin A}+\\frac{\\sin D}{\\sin E}\\right)+b\\left(\\frac{\\sin B}{\\sin C}+\\frac{\\sin F}{\\sin E}\\right)+c\\left(\\frac{\\sin D}{\\sin C}+\\frac{\\sin F}{\\sin A}\\right) \\\\\n\\geqslant & 2(a+b+c),\n\\end{aligned}\n$$\n所以\n$$\nR_A+R_C+R_E \\geqslant a+b+c=\\frac{p}{2} .\n$$\n(2)当 $a \\neq d$ 时,不妨设 $a>d$. 作\n$$\nF A_1 \\Perp A B, F E_1 \\Perp D E,\n$$\n连 $D E_1$, 连 $B A_1$ 延长交 $D E_1$ 于点 $C_1$, 则\n$$\n\\angle E_1 A_1 C_1=\\pi-A, \\angle A_1 C_1 E_1=\\pi-C, \\angle C_1 E_1 A_1=\\pi-E=\\pi-B\n$$\n且\n$$\n\\begin{aligned}\n& \\frac{\\sin A}{\\sin B}=\\frac{C_1 E_1}{A_1 C_1}, \\frac{\\sin B}{\\sin C}=\\frac{A_1 C_1}{A_1 E_1}, \\frac{\\sin C}{\\sin A}=\\frac{A_1 E_1}{C_1 E_1} . \\\\\n& a=d+A_1 E_1, e=b+E_1 C_1, c=f+C_1 A_1 .\n\\end{aligned}\n$$\n利用平均值不等式, 得\n$$\n\\begin{aligned}\n& 2\\left(R_A+R_B+R_C\\right) \\\\\n\\geqslant & 2(b+d+f)+\\frac{A_1 E_1 \\cdot A_1 C_1}{E_1 C_1}+\\frac{E_1 C_1 \\cdot A_1 E_1}{A_1 C_1}+\\frac{A_1 C_1 \\cdot E_1 C_1}{A_1 E_1} .\n\\end{aligned}\n$$\n再由排序不等式, 得\n$$\n\\frac{A_1 E_1 \\cdot A_1 C_1}{E_1 C_1}+\\frac{E_1 C_1 \\cdot A_1 E_1}{A_1 C_1}+\\frac{A_1 C_1 \\cdot E_1 C_1}{A_1 E_1} \\geqslant A_1 E_1+C_1 A_1+E_1 C_1 .\n$$\n从而\n$$\n2\\left(R_A+R_B+R_C\\right) \\geqslant 2(b+d+f)+A_1 E_1+C_1 A_1+E_1 C_1=p .\n$$\n综合 (1)、(2) 知命题成立.",
    "remark": "",
    "figures": []
}