{
    "source_file": "./raw_volume-zh/volume5/chapter5.tex",
    "problem_type": "proof",
    "problem": "例15. 给定两组数 $x_1, x_2, \\cdots, x_n$ 和 $y_1, y_2, \\cdots, y_n$, 现知\n$$\n\\begin{gathered}\nx_1>x_2>\\cdots>x_n>0, y_1>y_2>\\cdots>y_n>0, \\\\\nx_1>y_1, x_1+x_2>y_1+y_2, \\cdots, \\\\\nx_1+x_2+\\cdots+x_n>y_1+y_2+\\cdots+y_n .\n\\end{gathered}\n$$\n求证: 对于任何自然数 $k$,都有\n$$\nx_1^k+x_2^k+\\cdots+x_n^k>y_1^k+y_2^k+\\cdots+y_n^k .\n$$",
    "solution": "分析:我们猜想是否有如下的递推关系:\n$$\n\\begin{aligned}\n& x_1^k+x_2^k+\\cdots+x_n^k>x_1^{k-1} y_1+x_2^{k-1} y_2+\\cdots+x_n^{k-1} y_n, \\\\\n& x_1^{k-1} y_1+x_2^{k-1} y_2+\\cdots+x_n^{k-1} y_n>x_1^{k-2} y_1^2+x_2^{k-2} y_2^2+\\cdots+x_n^{k-2} y_n^2 \\text {, } \\\\\n& x_1 y_1^{k-1}+x_2 y_2^{k-1}+\\cdots+x_n y_n^{k-1}>y_1^k+y_2^k+\\cdots+y_n^k . \\\\\n&\n\\end{aligned}\n$$\n从而联想到构造辅助命题:\n若 $a_1>a_2>\\cdots>a_n>0$, 且满足题设的条件,那么:\n$$\na_1 x_1+a_2 x_2+\\cdots+a_n x_n>a_1 y_1+a_2 y_2+\\cdots+a_n y_n . \\label{(1)}\n$$\n证明因为 $a_1>a_2>\\cdots>a_n>0$, 故存在正数 $b_1, b_2, \\cdots b_{n-1}, b_n$ 使得:\n$$\n\\begin{gathered}\na_n=b_1, \\\\\na_{n-1}=b_1+b_2, \\\\\n\\cdots \\cdots \\cdots \\cdots \\cdots \\cdots \\cdots \\cdot \\cdots \\cdot \\cdots \\cdot \\cdots \\cdot \\cdots+b_{n-1}, \\\\\na_2=b_1+b_2+\\cdots \\cdots+b_n . \\\\\na_1=b_1+b_2+\\cdots+\n\\end{gathered}\n$$\n于是 $\\quad a_1 x_1+a_2 x_2+\\cdots+a_n x_n$\n$$\n\\begin{aligned}\n& =\\left(b_1+b_2+\\cdots+b_n\\right) x_1+\\left(b_1+b_2+\\cdots+b_{n-1}\\right) x_2+\\cdots+b_1 x_n \\\\\n& =b_1\\left(x_1+x_2+\\cdots+x_n\\right)+b_2\\left(x_1+x_2+\\cdots+x_{n-1}\\right)+\\cdots+b_n x_1 \\\\\n& >b_1\\left(y_1+y_2+\\cdots+y_n\\right)+b_2\\left(y_1+y_2+\\cdots+y_{n-1}\\right)+\\cdots+b_n y_1 \\\\\n& =\\left(b_1+b_2+\\cdots+b_n\\right) y_1+\\left(b_1+b_2+\\cdots+b_{n-1}\\right) y_2+\\cdots+b_1 y_n \\\\\n& =a_1 y_1+a_2 y_2+\\cdots+a_n y_n .\n\\end{aligned}\n$$\n故(1)式成立.\n再依次取 $a_i=x_i^{k-1}, x_i^{k-2} y_i, \\cdots, y_i^{k-1}(i=1,2, \\cdots, n)$, 利用不等式的传递性, 自大到小逐渐缩小, 即得所要证的不等式.",
    "remark": "",
    "figures": []
}