{
    "source_file": "./raw_volume-zh/volume6/chapter1-2.tex",
    "problem_type": "proof",
    "problem": "例2. 正整数数列 $c_1, c_2, \\cdots$ 满足下述条件:\n对任意正整数 $m 、 n$, 若 $1 \\leqslant m \\leqslant \\sum_{i=1}^n c_i$, 则存在正整数 $a_1, a_2, \\cdots, a_n$, 使得\n$$\nm=\\sum_{i=1}^n \\frac{c_i}{a_i}\n$$\n问: 对每个给定的 $i \\in \\mathbf{N}^*, c_i$ 的最大值为多少?",
    "solution": "解:我们证明: $c_1$ 的最大值为 2 , 而当 $i \\geqslant 2$ 时, $c_i$ 的最大值为 $4 \\times 3^{i-2}$.\n为此先证: <1>\n$$\nc_1 \\leqslant 2 \\text {, 而当 } i \\geqslant 2 \\text { 时, } c_i \\leqslant 4 \\times 3^{i-2} . \n$$\n事实上, 若 $c_1>1$, 取 $(m, n)=\\left(c_1-1,1\\right)$, 知存在 $a_1 \\in \\mathbf{N}^*$, 使得 $c_1- 1=\\frac{c_1}{a_1}$, 即 $a_1=\\frac{c_1}{c_1-1}=1+\\frac{1}{c_1-1}$, 仅当 $c_1=2$ 时, $a_1$ 为整数, 故 $c_1 \\leqslant 2$.\n现设<1>对 $i=1,2, \\cdots, k-1(k \\geqslant 2)$ 都成立, 取 $(m, n)=\\left(c_k, k\\right)$, 则存在 $a_1, \\cdots, a_k \\in \\mathbf{N}^*$, 使得 $c_k=\\frac{c_1}{a_1}+\\cdots+\\frac{c_k}{a_k}$. 这要求 $a_k \\geqslant 2$, 否则 $\\sum_{i=1}^{k-1} \\frac{c_i}{a_i}=$ 0 与 $a_i 、 c_i$ 为正整数矛盾.\n从而 $c_k \\leqslant \\frac{c_k}{2}+\\sum_{i=1}^{k-1} c_i$, 即 $c_k \\leqslant 2 \\sum_{i=1}^{k-1} c_i$. 所以 $c_k \\leqslant 2\\left(2+4+4 \\times 3+\\cdots+4 \\times 3^{k-3}\\right)=4 \\times 3^{k-2}$. 因此, 由第二数学归纳法知, 结论<1>成立.\n再证:\n<2> 当 $c_1=2, c_i=4 \\times 3^{i-2}(i \\geqslant 2)$ 时, 数列 $\\left\\{c_i\\right\\}$ 具有题给的性质.\n对 $n$ 归纳.\n当 $n=1$ 时, $m \\leqslant c_1=2$, 故 $m=1$ 或 2 . 若 $m=1$, 取 $a_1=2$ 即可,若 $m=2$, 取 $a_1=1$ 即可.\n假设当 $1,2, \\cdots, n-1$ 时, 题给性质满足.\n考虑 $n$ 的情形, 此时 $1 \\leqslant m \\leqslant \\sum_{i=1}^n c_i$.\n若 $m=1$, 取 $a_i=n c_i, i=1,2, \\cdots, n$ 即可;\n若 $2 \\leqslant m \\leqslant \\frac{c_n}{2}+1=\\left(\\sum_{i=1}^{n-1} c_i\\right)+1$, 令 $a_n=c_n$, 并对 $m-\\frac{c_n}{a_n}=m-1$ 用归纳假设, 可知<2>成立;\n若 $\\frac{1}{2} c_n+1<m \\leqslant c_n$, 取 $a_n=2$, 并对 $m-\\frac{c_n}{2}$ 用归纳假设即可;\n若 $c_n<m \\leqslant \\sum_{i=1}^n c_i$, 取 $a_n=1$, 并对 $m-c_n$ 用归纳假设即可.\n所以,结论<2>成立.\n综上可知, $c_1$ 的最大值为 2 , 而当 $i \\geqslant 2$ 时, $c_i$ 的最大值是 $4 \\times 3^{i-2}$.\n说明对比两个例子可发现, 用第二数学归纳法证题时, 一个思路是整体处理: 例 1 中对归纳假设中的 $n-1$ 个不等式求和; 另一个思路是将 $n$ 的情形归人 $1,2, \\cdots, n-1$ 中的某一种情形,这在例 2 的后半部分有明显的体现.",
    "remark": "",
    "figures": []
}