{
    "source_file": "./raw_volume-zh/volume7/chapter11.tex",
    "problem_type": "proof",
    "problem": "例5. 设 $P_1, P_2, \\cdots, P_n$ 是圆内接正 $n$ 边形, $P$ 是圆周上的任一点, 求证: $P P_1^4 \\cdot-P P_2^4+\\cdots+P P_n^4$ 是常数.",
    "solution": "证明:设圆心在原点, 圆的半径为 $r$.\n显然可令 $P_k=r \\mathrm{e}^{\\mathrm{i} \\cdot \\frac{2 k \\pi}{n}}(k=1,2, \\cdots, n), P=r \\mathrm{e}^{\\mathrm{i} \\theta}$, 于是\n$$\n\\begin{aligned}\n\\left|P P_k\\right|^4 & =\\left|P-P_k\\right|^4=\\left|r \\mathrm{e}^{\\mathrm{i} \\theta}-r \\mathrm{e}^{\\mathrm{i} \\cdot \\frac{2 k \\pi}{n}}\\right|^4 \\\\\n& =r^4\\left[\\left(\\mathrm{e}^{\\mathrm{i} \\theta}-\\mathrm{e}^{\\mathrm{i} \\cdot \\frac{2 k \\pi}{n}}\\right)\\left(\\mathrm{e}^{-\\mathrm{i} \\theta}-\\mathrm{e}^{-\\mathrm{i} \\cdot \\frac{2 k \\pi}{n}}\\right)\\right]^2\\left(\\text { 这里用到 }|z|^2=z \\cdot \\bar{z}\\right) \\\\\n& =r^4\\left[2-\\mathrm{e}^{\\mathrm{i} \\theta} \\mathrm{e}^{-\\mathrm{i} \\cdot \\frac{2 k \\pi}{n}}-\\mathrm{e}^{-\\mathrm{i} \\theta} \\mathrm{e}^{\\mathrm{i} \\cdot \\frac{2 k \\pi}{n}}\\right]^2 \\\\\n& =r^4\\left[6+\\mathrm{e}^{2 i \\theta} \\mathrm{e}^{-\\mathrm{i} \\cdot \\frac{4 k \\pi}{n}}+\\mathrm{e}^{-2 \\mathrm{i} \\theta} \\mathrm{e}^{\\mathrm{i} \\cdot \\frac{k k \\pi}{n}}-4 \\mathrm{e}^{\\mathrm{i} \\theta} \\mathrm{e}^{-\\mathrm{i} \\cdot \\frac{2 k \\pi}{n}}-4 \\mathrm{e}^{-\\mathrm{i} \\theta} \\mathrm{e}^{\\mathrm{i} \\cdot \\frac{2 k \\pi}{n}}\\right] .\n\\end{aligned}\n$$\n但是 $\\sum_{k=1}^n \\mathrm{e}^{ \\pm \\mathrm{i} \\cdot \\frac{4 k \\pi}{n}}=\\frac{\\mathrm{e}^{ \\pm \\mathrm{i} \\cdot \\frac{4 \\pi}{n}}\\left(1-\\mathrm{e}^{ \\pm \\mathrm{i} \\cdot \\frac{4 n \\pi}{n}}\\right)}{1-\\mathrm{e}^{\\mathrm{i} \\cdot \\frac{4 \\pi}{n}}}=0$,\n$$\n\\sum_{k=1}^n \\mathrm{e}^{ \\pm \\frac{2 k \\pi}{n}}=\\frac{\\mathrm{e}^{ \\pm \\mathrm{i} \\cdot \\frac{2 \\pi}{n}}\\left(1-\\mathrm{e}^{ \\pm \\mathrm{i} \\cdot \\frac{2 n \\pi}{n}}\\right)}{1-\\mathrm{e}^{ \\pm \\mathrm{i} \\cdot \\frac{2 \\pi}{n}}}=0,\n$$\n所以 $\\sum_{k=1}^n P P_k^4=6 n r^4$.\n它与点 $P$ 无关, 即它是一常数.",
    "remark": "注:(1) 从证明中易看出, $P P_1^2+P P_2^2+\\cdots+P P_n^2$ 也是一常数, 为 $2 n r^2$.\n(2) $\\mathrm{e}^{\\mathrm{i} \\theta}=\\cos \\theta+\\mathrm{i} \\sin \\theta$ 是复数欧拉公式.",
    "figures": []
}