{
    "source_file": "./raw_volume-zh/volume7/exercise3.tex",
    "problem_type": "proof",
    "problem": "问题11. 在 $\\triangle A B C$ 的边 $A B 、 B C 、 C A$ 上分别取点 $P 、 Q 、 S$. 证明: 以 $\\triangle A P S 、 \\triangle B Q P 、 \\triangle C S Q$ 的外心为顶点的三角形与 $\\triangle A B C$ 相似.",
    "solution": "证明: 如图(<FilePath:./images/volume7/figures/fig-c3a11.png>),设 $O_1 、 O_2 、 O_3$ 是 $\\triangle A P S 、 \\triangle B Q P 、 \\triangle C S Q$ 的外心, 作出六边形 $O_1 P O_2 Q O_3 S$ 后再由外心性质可知 $\\angle P O_1 S=2 \\angle A, \\angle Q O_2 P=2 \\angle B$,\n$$\n\\angle \\mathrm{SO}_3 \\mathrm{Q}=2 \\angle C \\text {. }\n$$\n所以 $\\angle P O_1 S+\\angle Q O_2 P+\\angle S O_3 Q=360^{\\circ}$. 从而又知\n$$\n\\angle O_1 P O_2+\\angle O_2 Q O_3+\\angle O_3 S O_1=360^{\\circ} \\text {. }\n$$\n将 $\\triangle O_2 Q_3$ 绕着 $O_3$ 点旋转到 $\\triangle K S O_3$,\n易判断 $\\triangle K S O_1 \\cong \\triangle O_2 P O_1$, 同时可得 $\\triangle \\mathrm{O}_1 \\mathrm{O}_2 \\mathrm{O}_3 \\cong \\triangle \\mathrm{O}_1 \\mathrm{KO}_3$.\n所以 $\\angle O_2 O_1 O_3=\\angle K O_1 O_3=\\frac{1}{2} \\angle O_2 O_1 K=\\frac{1}{2}\\left(\\angle O_2 O_1 S+\\angle S O_1 K\\right)= \\frac{1}{2}\\left(\\angle O_2 O_1 S+\\angle P O_1 O_2\\right)=\\frac{1}{2} \\angle P O_1 S=\\angle A$. 同理有 $\\angle O_1 O_2 O_3=\\angle B$. 故 $\\triangle O_1 O_2 O_3 \\backsim \\triangle A B C$.",
    "remark": "",
    "figures": [
        "./images/volume7/figures/fig-c3a11.png"
    ]
}