{
    "source_file": "./raw_volume-zh/volume11/chapter15.tex",
    "problem_type": "calculation",
    "problem": "例4. 设 $M=\\{1,2,3, \\cdots, 40\\}$, 求最小正整数 $n$, 使可将 $M$ 剖分成 $n$ 个两两不相交的子集且同一子集内任取 3 个数 $a, b, c$ (不必不相同)都有 $a \\neq b+c$.",
    "solution": "解:$n=4$ 时,将 $M$ 分解为下列 4 个两两不相交的子集: $A=\\{5,6,7$, $8,9,32,33,34,35,36\\}, B=\\{14,15,16, \\cdots, 25,26,27\\}, C=\\{2,3$, $11,12,29,30,38,39\\}, D=\\{1,4,10,13,28,31,37,40\\}$, 则同一子集内任取 3 个数 $a, b, c$ (不必不相同) 都有 $a \\neq b+c$, 故所求最小正整数 $n \\leqslant 4$.\n其次,假设可将 $M$ 分成 3 个两两不相交的子集 $A, B, C$ 使得在同一子集内任取 3 个数 $a, b, c$ (不必不相同)都有 $a \\neq b+c$. 不妨设 $|A| \\geqslant|B| \\geqslant|C|$,\n且 $A$ 中元素从小到大排列为 $a_1, a_2, \\cdots, a_{|A|}$. 于是 $a_1, a_2, \\cdots, a_{|A|}$, 以及 $a_2- a_1, a_3-a_1, \\cdots, a_{|A|}-a_1$ 都是 $M$ 中的两两不同的数(事实上, 由 $0<a_i-a_1<a_i$ 知 $a_i-a_1 \\in M(i=1,2, \\cdots,|A|)$, 且若 $a_i-a_1=a_j$ 则 $a_i=a_1+a_j$, 这与假设矛盾). 因为这些数共有 $2|A|-1$ 个, 所以 $2|A|-1 \\leqslant 40,|A| \\leqslant 20$, 其次 $3|A| \\geqslant|A|+|B|+|C|=40$, 所以 $|A| \\geqslant 14$, 并且 $|B| \\geqslant \\frac{1}{2}(|B|+|C|)=\\frac{1}{2}(40-|A|)$. 从而元素对集合 $A \\times B=\\{(a, b) \\mid a \\in A$, $b \\in B\\}$ 中元素个数为 $|A \\times B|=|A| \\cdot|B| \\geqslant \\frac{1}{2}|A|(40-|A|)$. 而对任意元素对 $(a, b) \\in A \\times B, a+b$ 至少为 2 , 至多为 80 , 至多只有 79 种可能, 且 $14 \\leqslant |A| \\leqslant 20$. 又二次函数 $f(t)=\\frac{1}{2} t(40-t)$ 在区间 $[14,20]$ 上的最小值为 $\\min \\{f(14), f(20)\\}=\\min \\left\\{\\frac{1}{2} \\times 14 \\times(40-14), \\frac{1}{2} \\times 20 \\times(40-20)\\right\\}=$ 182. 故 $|A \\times B| \\geqslant 182$, 由抽庶原理知 $A \\times B$ 中至少有 $\\left[\\frac{182-1}{79}\\right]+1=3$ 个不同元素 $\\left(a_1, b_1\\right),\\left(a_2, b_2\\right),\\left(a_3, b_3\\right)$ 满足 $a_1+b_1=a_2+b_2=a_3+b_3$.\n若 $a_1, a_2, a_3$ 中有两个相等, 则对应的 $b_i$ 也相等.\n这与 $\\left(a_1, b_1\\right),\\left(a_2\\right.$, $\\left.b_2\\right),\\left(a_3, b_3\\right)$ 两两不同矛盾,故 $a_1, a_2, a_3$ 两两不同, 从而 $b_1, b_2, b_3$ 也两两不同.\n不妨设 $a_1<a_2<a_3$, 从而 $b_1>b_2>b_3$. 并且对任意 $1 \\leqslant i<j \\leqslant 3, a_j- a_i$ 仍在 $M$ 中但不在 $A$ 中, 同理对任意 $1 \\leqslant i<j \\leqslant 3, b_i-b_j \\in M$, 但 $b_i- b_j \\notin B$, 故三个差 $a_2-a_1=b_1-b_2, a_3-a_1=b_1-b_3, a_3-a_2=b_2-b_3 \\notin A \\cup B$, 从而它们都属于 $C=M(A \\cup B)$. 令 $a=a_3-a_1, b=a_2-a_1, c= a_3-a_2$, 则 $a=b+c$, 矛盾,所以 $n$ 的最小值 $\\geqslant 4$.\n综上可知, 所求 $n$ 的最小值为 4 .",
    "remark": "",
    "figures": []
}