{
    "source_file": "./raw_volume-zh/volume13/chapter9.tex",
    "problem_type": "calculation",
    "problem": "例3. 有 10 人到书店买书, 已知每人都买了三种书, 任何两个人所买的书中都至少有一种相同.\n问: 买的人数最多的一种书最少有几人购买.",
    "solution": "解:共卖出 $n$ 种书, 第 $i$ 人买的书的集合为 $A_i(i=1,2, \\cdots, 10)$. 构造集合元素关系表,设第 $i$ 行有 $m_i$ 个 1 .\n估计各元素出现的总次数,有\n$$\n\\sum_{i=1}^n m_i=S=\\sum_{i=1}^{10}\\left|A_i\\right|=\\sum_{i=1}^{10} 3=30\n$$\n再计算各元素在交集中出现的总次数,有\n$$\n\\sum_{i=1}^n \\mathrm{C}_{m_i}^2=\\sum_{1 \\leqslant i<j \\leqslant 10}\\left|A_i \\cap A_j\\right|\n$$\n设 $m_i$ 中的最大者为 $m$, 则\n$$\n\\begin{aligned}\n90 & =2 \\mathrm{C}_{10}^2=2 \\sum_{1 \\leqslant i<j \\leqslant 10} 1 \\leqslant 2 \\sum_{1 \\leqslant i<j \\leqslant 10}\\left|A_i \\cap A_j\\right| \\\\\n& =2 \\sum_{i=1}^n \\mathrm{C}_{m_i}^2=\\sum_{i=1}^n m_i^2-\\sum_{i=1}^n m_i=\\sum_{i=1}^n m_i^2-30 \\\\\n& \\leqslant \\sum_{i=1}^n\\left(m_i \\cdot m\\right)-30=m \\sum_{i=1}^n m_i-30 \\\\\n& =30(m-1) .\n\\end{aligned}\n$$\n解此不等式, 得 $m \\geqslant 4$. 若 $m=4$, 则不等式 (1) 成立等号, 于是所有 $m_i=4(i=1,2, \\cdots, n)$. 这样有 $4 n=\\sum_{i=1}^n m_i=30$, 所以 $4 \\mid 30$, 矛盾.\n于是 $m \\geqslant 5$.\n当 $m=5$ 时, 由 $m$ 的最大性, 所有 $m_i \\leqslant 5$, 有 $30=\\sum_{i=1}^n m_i \\leqslant 5 n, n \\geqslant 6$. 我们取 $n=6$, 得到合乎条件的构造如下表:\n\\begin{tabular}{|c|c|c|c|c|c|c|c|c|c|c|}\n\\hline & $A_1$ & $A_2$ & $A_3$ & $A_4$ & $A_5$ & $A_6$ & $A_7$ & $A_8$ & $A_9$ & $A_{10}$ \\\\\n\\hline 1 & $*$ & $*$ & $*$ & $*$ & $*$ & & & & & \\\\\n\\hline 2 & $*$ & $*$ & & & & $*$ & $*$ & $*$ & & \\\\\n\\hline 3 & $*$ & & $*$ & & & $*$ & & & $*$ & $*$ \\\\\n\\hline 4 & & & & $*$ & $*$ & $*$ & $*$ & & $*$ & \\\\\n\\hline 5 & $\\vdots$ & & $*$ & $*$ & & & $*$ & $*$ & & $*$ \\\\\n\\hline 6 & & $*$ & & & $*$ & & & $*$ & $*$ & $*$ \\\\\n\\hline\n\\end{tabular}\n故 $m$ 的最小值为 5 .",
    "remark": "",
    "figures": []
}