{
    "source_file": "./raw_volume-zh/volume13/exercise7.tex",
    "problem_type": "calculation",
    "problem": "问题5. 在 $1,2, \\cdots, 20$ 中最多能选出多少个数, 使其中任何一个选出来的数都不是另一个选出来的数的 2 倍.\n并问: 这样的取数方法有多少种?",
    "solution": "令 $A_1=\\{1,2,4,8,16\\}, A_2=\\{3,6,12\\}, A_3=\\{5,10,20\\}$, $A_4=\\{7,14\\}, A_5=\\{9,18\\}, A_6=\\{11\\}, A_7=\\{13\\}, A_8=\\{15\\}, A_9=\\{17\\}, A_{10}=\\{19\\}$. 因为 $\\{1,2\\} 、\\{4,8\\} 、\\{16\\}$ 三个集合的每一个中最多取出一个数, 所以 $A_1$ 中最多可取 3 个数.\n如果 $A_1$ 中取出 3 个数, 则必取 16 , 于是不能取 8 , 所以必取 4 , 于是不能取 2 , 所以必取 1 , 因而只有唯一的方法在 $A_1$ 中取出 3 个数.\n同理可知, $A_2$ 和 $A_3$ 中分别最多可取 2 个数, 而且只有唯一的方法取出 2 个数.\n$A_4 、 A_5$ 中都最多可取 1 个数, 但都有 2 种方法取出 2 个数.\n其他集合都最多取出 1 . 个数, 且只有唯一的取法.\n于是, 最多可取出 $3+2+ 2+(1+1)+1 \\cdot 5=14$ 个数.\n而且等号可以成立.\n取数共有 $2 \\cdot 2=4$ 种方法.\n取出来的数构成的集合为 $X \\cup Y_i(i=1 、 2 、 3 、 4)$. 其中 $X=\\{1,4,16,3$, $12,5,20,11,13,15,17,19\\}, Y_1=\\{7,18\\}, Y_2=\\{7,9\\}, Y_3=\\{14$, $18\\}, Y_4=\\{14,9\\}$. 故取出来的数的个数的最大值为 14 .\n另解: 令 $A_1=\\{1,2\\}, A_2=\\{3,6\\}, A_3=\\{4,8\\}, A_4=\\{5,10\\}$, $A_5=\\{7,14\\}, A_6=\\{9,18\\}$. 则每个集合中最多取出一个数, 所以这些集合中最多可取 6 个数.\n这些集合外还有 8 个数, 所以最多可取出 $6+8=14$ 个数.\n若取出 14 个数, 则必取 $11 、 12 、 13 、 15 、 16 、 17 、 19 、 20$. 注意取了 $12 、 16 、 20$ 后不能取 $6 、 8 、 10$, 所以必取 $3 、 4 、 5$. 又取了 4 后不能取 2 , 所以必取 1 . 剩下 $A_5 、 A_6$ 中各取出 1 个数, 共有 $2 \\cdot 2=4$ 种方法.",
    "remark": "",
    "figures": []
}